pytest_test_tracer_for_pytest/__init__.py
pytest_test_tracer_for_pytest/constants.py
pytest_test_tracer_for_pytest/hooks.py
pytest_test_tracer_for_pytest/plugin.py
pytest_test_tracer_for_pytest-0.1.1.dist-info/LICENSE
pytest_test_tracer_for_pytest-0.1.1.dist-info/METADATA
pytest_test_tracer_for_pytest-0.1.1.dist-info/WHEEL
pytest_test_tracer_for_pytest-0.1.1.dist-info/entry_points.txt
pytest_test_tracer_for_pytest-0.1.1.dist-info/top_level.txt
pytest_test_tracer_for_pytest-0.1.1.dist-info/RECORD
