Metadata-Version: 2.1
Name: pytest-test_tracer_for_pytest
Version: 0.1.1
Summary: A plugin that allows coll test data for use on Test Tracer
Author-email: Gavin Clark <testtracer.io@gmail.com>
Maintainer-email: Gavin Clark <testtracer.io@gmail.com>
License: 
Project-URL: Repository, https://github.com/testreporter/test-tracer-for-pytest
Classifier: Framework :: Pytest
Classifier: Development Status :: 4 - Beta
Classifier: Intended Audience :: Developers
Classifier: Topic :: Software Development :: Testing
Classifier: Operating System :: OS Independent
Classifier: Programming Language :: Python
Classifier: Programming Language :: Python :: 3.8
Classifier: Programming Language :: Python :: 3.9
Classifier: Programming Language :: Python :: 3.10
Classifier: Programming Language :: Python :: 3.11
Classifier: Programming Language :: Python :: 3.12
Classifier: Programming Language :: Python :: 3 :: Only
Classifier: Programming Language :: Python :: Implementation :: CPython
Classifier: Programming Language :: Python :: Implementation :: PyPy
Classifier: License :: OSI Approved :: MIT License
Requires-Python: >=3.8
License-File: LICENSE
Requires-Dist: pytest >=6.2.0
